janux_auth_gateway/__init__.py
janux_auth_gateway/auth/__init__.py
janux_auth_gateway/auth/jwt.py
janux_auth_gateway/auth/key_pairs.py
janux_auth_gateway/auth/passwords.py
janux_auth_gateway/config/__init__.py
janux_auth_gateway/config/config.py
janux_auth_gateway/database/__init__.py
janux_auth_gateway/database/mongoDB.py
janux_auth_gateway/database/postgreSQL.py
janux_auth_gateway/database/postgreSQL_base.py
janux_auth_gateway/errors/__init__.py
janux_auth_gateway/errors/exceptions.py
janux_auth_gateway/errors/handlers.py
janux_auth_gateway/main.py
janux_auth_gateway/models/__init__.py
janux_auth_gateway/models/mongoDB/admin_model.py
janux_auth_gateway/models/mongoDB/roles_model.py
janux_auth_gateway/models/mongoDB/user_model.py
janux_auth_gateway/models/postgreSQL/admin_model.py
janux_auth_gateway/models/postgreSQL/roles_model.py
janux_auth_gateway/models/postgreSQL/user_model.py
janux_auth_gateway/routers/__init__.py
janux_auth_gateway/routers/admin_router.py
janux_auth_gateway/routers/auth_router.py
janux_auth_gateway/routers/base_router.py
janux_auth_gateway/routers/user_router.py
janux_auth_gateway/schemas/__init__.py
janux_auth_gateway/schemas/response_schema.py
janux_auth_gateway/schemas/token_schema.py
janux_auth_gateway/schemas/user_schema_mongo.py
janux_auth_gateway/schemas/user_schema_postgres.py
janux_auth_gateway/utils/__init__.py
janux_auth_gateway/utils/email_utils.py
janux_auth_gateway-2.0.1.dist-info/LICENSE
janux_auth_gateway-2.0.1.dist-info/METADATA
janux_auth_gateway-2.0.1.dist-info/WHEEL
janux_auth_gateway-2.0.1.dist-info/entry_points.txt
janux_auth_gateway-2.0.1.dist-info/RECORD
