Metadata-Version: 2.3
Name: JANUX-auth-gateway
Version: 2.0.1
Summary: A modular OAuth2 and JWT authentication gateway for FastAPI microservices.
License: Apache-2.0
Author: FOX Techniques
Author-email: ali.nabbi@fox-techniques.com
Requires-Python: >=3.10,<4.0
Classifier: License :: OSI Approved :: Apache Software License
Classifier: Programming Language :: Python :: 3
Classifier: Programming Language :: Python :: 3.10
Classifier: Programming Language :: Python :: 3.11
Classifier: Programming Language :: Python :: 3.12
Classifier: Programming Language :: Python :: 3.13
Requires-Dist: alembic (>=1.15.2,<2.0.0)
Requires-Dist: argon2-cffi (>=23.1.0,<24.0.0)
Requires-Dist: asyncpg (>=0.30.0,<0.31.0)
Requires-Dist: bcrypt (>=4.2.1,<5.0.0)
Requires-Dist: beanie (>=1.29.0,<2.0.0)
Requires-Dist: coloredlogs (>=15.0.1,<16.0.0)
Requires-Dist: fastapi[standard] (>=0.115.6,<0.116.0)
Requires-Dist: hestia-logger (>=1.1.0,<2.0.0)
Requires-Dist: motor (==3.6.1)
Requires-Dist: passlib[bcrypt] (>=1.7.4,<2.0.0)
Requires-Dist: pyjwt[crypto] (>=2.10.1,<3.0.0)
Requires-Dist: pymongo (==4.9)
Requires-Dist: python-dotenv (>=1.0.1,<2.0.0)
Requires-Dist: python-json-logger (>=3.2.1,<4.0.0)
Requires-Dist: python-multipart (>=0.0.20,<0.0.21)
Requires-Dist: redis (>=5.2.1,<6.0.0)
Requires-Dist: sqlalchemy (>=2.0.40,<3.0.0)
Requires-Dist: uvicorn (>=0.34.0,<0.35.0)
Project-URL: Homepage, https://github.com/fox-techniques/janux-auth-gateway
Project-URL: Repository, https://github.com/fox-techniques/janux-auth-gateway
